conformly/__init__.py
conformly/_builtin_parsing_adapters.py
conformly/core.py
conformly/py.typed
conformly/types.py
conformly/constraints/__init__.py
conformly/constraints/base.py
conformly/constraints/enum.py
conformly/constraints/mapping.py
conformly/constraints/numeric.py
conformly/constraints/string.py
conformly/constraints/types.py
conformly/generator/__init__.py
conformly/generator/orchestration.py
conformly/generator/protocol.py
conformly/generator/registry.py
conformly/generator/types/__init__.py
conformly/generator/types/boolean.py
conformly/generator/types/enum.py
conformly/generator/types/float.py
conformly/generator/types/integer.py
conformly/generator/types/string.py
conformly/parsing/__init__.py
conformly/parsing/protocol.py
conformly/parsing/registry.py
conformly/parsing/adapters/__init__.py
conformly/parsing/adapters/dataclass_adapter.py
conformly/planner/__init__.py
conformly/planner/plan_field.py
conformly/planner/plan_session.py
conformly/planner/planned_task.py
conformly/resolver/__init__.py
conformly/resolver/field.py
conformly/resolver/model.py
conformly/resolver/resolve.py
conformly/resolver/semantics/__init__.py
conformly/resolver/semantics/boolean.py
conformly/resolver/semantics/enum.py
conformly/resolver/semantics/numeric.py
conformly/resolver/semantics/object.py
conformly/resolver/semantics/string.py
conformly/specs/__init__.py
conformly/specs/field.py
conformly/specs/model.py
conformly-0.3.3.dist-info/licenses/LICENSE
conformly-0.3.3.dist-info/METADATA
conformly-0.3.3.dist-info/WHEEL
conformly-0.3.3.dist-info/top_level.txt
conformly-0.3.3.dist-info/RECORD
