Metadata-Version: 2.4
Name: conformly
Version: 0.3.3
Summary: Generate valid & invalid test data from your typed schemas
Author-email: Nikita Shabanov <nik.shabanov2024@gmail.com>
License: MIT
Project-URL: Homepage, https://github.com/nashabanov/conformly
Project-URL: Repository, https://github.com/nashabanov/conformly.git
Project-URL: Issues, https://github.com/nashabanov/conformly/issues
Keywords: testing,fixtures,test-data,dataclasses,validation
Classifier: Development Status :: 3 - Alpha
Classifier: Intended Audience :: Developers
Classifier: License :: OSI Approved :: MIT License
Classifier: Programming Language :: Python :: 3
Classifier: Programming Language :: Python :: 3.13
Classifier: Topic :: Software Development :: Testing
Requires-Python: >=3.13
License-File: LICENSE
Requires-Dist: rstr>=3.2.2
Dynamic: license-file
